eth_pretty_events/__init__.py
eth_pretty_events/address_book.py
eth_pretty_events/alchemy_utils.py
eth_pretty_events/block_tree.py
eth_pretty_events/cli.py
eth_pretty_events/decode_events.py
eth_pretty_events/discord.py
eth_pretty_events/event_filter.py
eth_pretty_events/event_parser.py
eth_pretty_events/event_subscriptions.py
eth_pretty_events/flask_app.py
eth_pretty_events/jinja2_ext.py
eth_pretty_events/outputs.py
eth_pretty_events/print_output.py
eth_pretty_events/pubsub.py
eth_pretty_events/render.py
eth_pretty_events/types.py
eth_pretty_events/templates/ERC20-transfer.md.j2
eth_pretty_events/templates/ERC4626-transactions.md.j2
eth_pretty_events/templates/generic-event-on-error.md.j2
eth_pretty_events/templates/generic-event.md.j2
eth_pretty_events-0.1.10.dist-info/licenses/LICENSE.txt
eth_pretty_events-0.1.10.dist-info/METADATA
eth_pretty_events-0.1.10.dist-info/WHEEL
eth_pretty_events-0.1.10.dist-info/entry_points.txt
eth_pretty_events-0.1.10.dist-info/top_level.txt
eth_pretty_events-0.1.10.dist-info/RECORD
