Metadata-Version: 2.4
Name: eth-pretty-events
Version: 0.1.10
Summary: Add a short description here!
Home-page: https://github.com/pyscaffold/pyscaffold/
Author: Guillermo M. Narvaja
Author-email: guillermo.narvaja@radiocut.fm
License: MIT
Project-URL: Documentation, https://pyscaffold.org/
Platform: any
Classifier: Development Status :: 4 - Beta
Classifier: Programming Language :: Python
License-File: LICENSE.txt
Requires-Dist: importlib-metadata; python_version < "3.8"
Requires-Dist: web3>=7.8
Requires-Dist: PyYAML
Provides-Extra: testing
Requires-Dist: setuptools; extra == "testing"
Requires-Dist: pytest; extra == "testing"
Requires-Dist: pytest-cov; extra == "testing"
Requires-Dist: Jinja2; extra == "testing"
Requires-Dist: factory_boy; extra == "testing"
Requires-Dist: pytest-asyncio; extra == "testing"
Requires-Dist: pytest-aiohttp; extra == "testing"
Provides-Extra: pubsub
Requires-Dist: google-cloud-pubsub; extra == "pubsub"
Provides-Extra: templates
Requires-Dist: Jinja2; extra == "templates"
Provides-Extra: flask
Requires-Dist: Flask; extra == "flask"
Dynamic: license-file
